cribl/__init__.py
cribl/appscopelibentries.py
cribl/appscopelibentry.py
cribl/authenticationsettings.py
cribl/authorizations.py
cribl/authtoken.py
cribl/branches.py
cribl/bulletinmessage.py
cribl/bulletinmessages.py
cribl/bytes.py
cribl/cancelrunninggroup.py
cribl/certificate.py
cribl/certificates.py
cribl/changedfiles.py
cribl/changelogs.py
cribl/changelogviewstate.py
cribl/clientroles.py
cribl/cluis.py
cribl/collector.py
cribl/collectorobject.py
cribl/commit.py
cribl/condition.py
cribl/conditions.py
cribl/configgroup.py
cribl/configuredcollectors.py
cribl/container.py
cribl/countfile.py
cribl/createpipeline.py
cribl/criblmetadata.py
cribl/criblssettings.py
cribl/criblsystemsettings.py
cribl/currentconfig.py
cribl/databaseconnection.py
cribl/databaseconnectionconfigid.py
cribl/datasample.py
cribl/datasampleid.py
cribl/dataset.py
cribl/datasetobject.py
cribl/datasetobjects.py
cribl/datasets.py
cribl/destinationqueue.py
cribl/diagbundle.py
cribl/diagbundles.py
cribl/distributeddeployment.py
cribl/edgehostfiles.py
cribl/edgelisting.py
cribl/eventbreaker.py
cribl/eventbreakerid.py
cribl/eventbreakerondata.py
cribl/events.py
cribl/executedistributedupgrade.py
cribl/executorid.py
cribl/executorobject.py
cribl/existingdiagbundles.py
cribl/feature.py
cribl/features.py
cribl/fieldsummaries.py
cribl/fleetmapping.py
cribl/fleetmappings.py
cribl/fleetorworkergroup.py
cribl/functionid.py
cribl/gitsettings.py
cribl/givecriblversion.py
cribl/globalvariable.py
cribl/globalvariableid.py
cribl/grokfile.py
cribl/grokfiles.py
cribl/groupbundle.py
cribl/groups.py
cribl/healthinfo.py
cribl/hostmetadatastructure.py
cribl/idpauth.py
cribl/idpuserauth.py
cribl/internalsystemmetrics.py
cribl/javascriptexpression.py
cribl/job.py
cribl/jobinfos.py
cribl/jobresult.py
cribl/jobresults.py
cribl/jobstatus.py
cribl/keymetadataentities.py
cribl/keymetadataentity.py
cribl/kmsconfig.py
cribl/kmshealth.py
cribl/latestpq.py
cribl/license.py
cribl/licenses.py
cribl/licenseusagemetrics.py
cribl-1.0.0.dist-info/LICENSE.md
cribl-1.0.0.dist-info/METADATA
cribl-1.0.0.dist-info/WHEEL
cribl-1.0.0.dist-info/top_level.txt
cribl-1.0.0.dist-info/RECORD
